<?xml version="1.0" encoding="UTF-8"?>
<root>
  <item>
    <id>3s5po2cggps8vqj0esl47q2ju6</id>
    <last_activity>1480937232</last_activity>
    <expiration>1481542032</expiration>
    <data></data>
  </item>
  <item>
    <id>40vd3hqpqv701lp0jd14gbguk7</id>
    <last_activity>1485255836</last_activity>
    <expiration>1485860636</expiration>
    <data></data>
  </item>
  <item>
    <id>8nlgpf83756um29q9jurhq70g1</id>
    <last_activity>1501683057</last_activity>
    <expiration>1502287857</expiration>
    <data></data>
  </item>
  <item>
    <id>poqsotlr3hej5p92bhfrcbb1n0</id>
    <last_activity>1480681194</last_activity>
    <expiration>1481285994</expiration>
    <data></data>
  </item>
  <item>
    <id>rdpkcrjf1sb2pjsgejtjovfgf2</id>
    <last_activity>1497043288</last_activity>
    <expiration>1497648088</expiration>
    <data></data>
  </item>
  <item>
    <id>tjn0r6g1egn1554d7cir73lf31</id>
    <last_activity>1485255859</last_activity>
    <expiration>1485860659</expiration>
    <data></data>
  </item>
  <item>
    <id>vd9h3cv5abh7htmg9j8rbv7at3</id>
    <last_activity>1497619097</last_activity>
    <expiration>1498223897</expiration>
    <data></data>
  </item>
</root>
